demeter/__init__.py
demeter/app.py
demeter/templates/index.html
demeter/templates/login.html
demeter_tod-3.1.dist-info/METADATA
demeter_tod-3.1.dist-info/WHEEL
demeter_tod-3.1.dist-info/entry_points.txt
demeter_tod-3.1.dist-info/RECORD
