Metadata-Version: 2.4
Name: demeter-tod
Version: 3.1
Summary: A simple but powerful Flask application for receiving, logging, and monitoring webhooks. Built for developers who need to debug and test webhook integrations.
Project-URL: Homepage, https://github.com/joelindra/Demeter
Project-URL: Issues, https://github.com/joelindra/Demeter/issues
Author-email: Joel Indra <anonre@anonre.com>
Classifier: License :: OSI Approved :: MIT License
Classifier: Operating System :: OS Independent
Classifier: Programming Language :: Python :: 3
Requires-Python: >=3.7
Requires-Dist: flask
